LAB2/Problem 1/seq_detect_mealy.v
`timescale 1ns / 1ps

module seq_detect_mealy(input clk,din,reset,output y);
parameter A=2'd0,B=2'd1,C=2'd2,D=2'd3;
reg [1:0] state,next_state;
always@(*) begin
case(state)
A:next_state = din?B:A;
B:next_state = din?C:A;
C:next_state = din?C:D;
D:next_state = din?B:A;
endcase
end
always@(posedge clk) begin
if(reset) state<=A;
else state<=next_state;
end
assign y = (state==D)&din;
endmodule

fsm_assignments/Problem 1/tb.v
`timescale 1ns / 1ps

module tb();
    reg clk, din, reset;
    wire y;
    seq_detect_mealy uut (.clk(clk),.din(din),.reset(reset),.y(y));
    always #5 clk = ~clk;
    integer i;
    initial begin
  $dumpfile("wave1.vcd");   // file to dump signals
  $dumpvars(1, tb);  // dump all signals in tb
end

    initial begin

        clk = 0; din = 0; reset = 1;
        #20 reset = 0; 
        $display("\n Stream 1:1101");
        for (i=0; i<4; i=i+1) begin
            case (i)
                0: din = 1;
                1: din = 1;
                2: din = 0;
                3: din = 1;
            endcase
            @(posedge clk);
            $display("Cycle %0d: din=%b, state=%d, y=%b", i, din, uut.state, y);
        end
        $display("\n Stream 2: Overlap 1101101");
        for (i=0; i<7; i=i+1) begin
            case (i)
                0: din = 1;
                1: din = 1;
                2: din = 0;
                3: din = 1;
                4: din = 1;
                5: din = 0;
                6: din = 1;
            endcase
            @(posedge clk);
            $display("Cycle %0d: din=%b, state=%d, y=%b", i, din, uut.state, y);
        end
        $display("\n Stream 3:1011011011001101");
        for (i=0; i<16; i=i+1) begin
            case (i)
                0: din = 1;
                1: din = 0;
                2: din = 1;
                3: din = 1;
                4: din = 0;
                5: din = 1;
                6: din = 1;
                7: din = 0;
                8: din = 1;
                9: din = 1;
                10: din = 0;
                11: din = 0;
                12: din = 1;
                13: din = 1;
                14: din = 0;
                15: din = 1;
            endcase
            @(posedge clk);
            $display("Cycle %0d: din=%b, state=%d, y=%b", i, din, uut.state, y);
        end
        $display("\n Stream 4:111101101");
        for (i=0; i<9; i=i+1) begin
            case (i)
                0: din = 1;
                1: din = 1;
                2: din = 1;
                3: din = 1;
                4: din = 0;
                5: din = 1;
                6: din = 1;
                7: din = 0;
                8: din = 1;
            endcase
            @(posedge clk);
            $display("Cycle %0d: din=%b, state=%d, y=%b", i, din, uut.state, y);
        end
        $stop;
    end

endmodule

LAB2/Problem 1/wave1.vcd
$date
	Sun Aug 17 12:21:22 2025
$end
$version
	Icarus Verilog
$end
$timescale
	1ps
$end
$scope module tb $end
$var wire 1 ! y $end
$var reg 1 " clk $end
$var reg 1 # din $end
$var reg 1 $ reset $end
$var integer 32 % i [31:0] $end
$upscope $end
$enddefinitions $end
$comment Show the parameter values. $end
$dumpall
$end
#0
$dumpvars
bx %
1$
0#
0"
0!
$end
#5000
1"
#10000
0"
#15000
1"
#20000
0"
1#
b0 %
0$
#25000
b1 %
1"
#30000
0"
#35000
0#
b10 %
1"
#40000
0"
#45000
1!
1#
b11 %
1"
#50000
0"
#55000
0!
b0 %
1"
#60000
0"
#65000
b1 %
1"
#70000
0"
#75000
0#
b10 %
1"
#80000
0"
#85000
1!
1#
b11 %
1"
#90000
0"
#95000
0!
b100 %
1"
#100000
0"
#105000
0#
b101 %
1"
#110000
0"
#115000
1!
1#
b110 %
1"
#120000
0"
#125000
0!
b0 %
1"
#130000
0"
#135000
0#
b1 %
1"
#140000
0"
#145000
1!
1#
b10 %
1"
#150000
0"
#155000
0!
b11 %
1"
#160000
0"
#165000
0#
b100 %
1"
#170000
0"
#175000
1!
1#
b101 %
1"
#180000
0"
#185000
0!
b110 %
1"
#190000
0"
#195000
0#
b111 %
1"
#200000
0"
#205000
1!
1#
b1000 %
1"
#210000
0"
#215000
0!
b1001 %
1"
#220000
0"
#225000
0#
b1010 %
1"
#230000
0"
#235000
b1011 %
1"
#240000
0"
#245000
0!
1#
b1100 %
1"
#250000
0"
#255000
b1101 %
1"
#260000
0"
#265000
0#
b1110 %
1"
#270000
0"
#275000
1!
1#
b1111 %
1"
#280000
0"
#285000
0!
b0 %
1"
#290000
0"
#295000
b1 %
1"
#300000
0"
#305000
b10 %
1"
#310000
0"
#315000
b11 %
1"
#320000
0"
#325000
0#
b100 %
1"
#330000
0"
#335000
1!
1#
b101 %
1"
#340000
0"
#345000
0!
b110 %
1"
#350000
0"
#355000
0#
b111 %
1"
#360000
0"
#365000
1!
1#
b1000 %
1"
